odoo/addons/pos_payment_method_cashdro/README.rst
odoo/addons/pos_payment_method_cashdro/__init__.py
odoo/addons/pos_payment_method_cashdro/__manifest__.py
odoo/addons/pos_payment_method_cashdro/i18n/it.po
odoo/addons/pos_payment_method_cashdro/i18n/pos_payment_method_cashdro.pot
odoo/addons/pos_payment_method_cashdro/models/__init__.py
odoo/addons/pos_payment_method_cashdro/models/pos_payment_method.py
odoo/addons/pos_payment_method_cashdro/models/pos_session.py
odoo/addons/pos_payment_method_cashdro/readme/CONFIGURE.md
odoo/addons/pos_payment_method_cashdro/readme/CONTRIBUTORS.md
odoo/addons/pos_payment_method_cashdro/readme/DESCRIPTION.md
odoo/addons/pos_payment_method_cashdro/readme/ROADMAP.md
odoo/addons/pos_payment_method_cashdro/readme/USAGE.md
odoo/addons/pos_payment_method_cashdro/static/description/icon.png
odoo/addons/pos_payment_method_cashdro/static/description/index.html
odoo/addons/pos_payment_method_cashdro/static/description/logo.png
odoo/addons/pos_payment_method_cashdro/static/src/js/models.esm.js
odoo/addons/pos_payment_method_cashdro/static/src/js/payment_cashdro.esm.js
odoo/addons/pos_payment_method_cashdro/views/pos_payment_method_views.xml
odoo_addon_pos_payment_method_cashdro-17.0.1.0.0.4.dist-info/METADATA
odoo_addon_pos_payment_method_cashdro-17.0.1.0.0.4.dist-info/WHEEL
odoo_addon_pos_payment_method_cashdro-17.0.1.0.0.4.dist-info/top_level.txt
odoo_addon_pos_payment_method_cashdro-17.0.1.0.0.4.dist-info/RECORD
